{
  "symbol": "DIS",
  "year": 2022,
  "report_type": "YearlyIncomeStatement",
  "items": {
    "Tax Effect Of Unusual Items": -1105136000.0,
    "Tax Rate For Calcs": 0.289,
    "Normalized EBITDA": 15935000000.0,
    "Total Unusual Items": -3824000000.0,
    "Total Unusual Items Excluding Goodwill": -3824000000.0,
    "Net Income From Continuing Operation Net Minority Interest": 2354000000.0,
    "Reconciled Depreciation": 5369000000.0,
    "Reconciled Cost Of Revenue": 59201000000.0,
    "EBITDA": 12111000000.0,
    "EBIT": 6742000000.0,
    "Net Interest Income": -1549000000.0,
    "Interest Expense": 1973000000.0,
    "Interest Income": 424000000.0,
    "Normalized Income": 5072864000.0,
    "Net Income From Continuing And Discontinued Operation": 2354000000.0,
    "Total Expenses": 79906000000.0,
    "Diluted Average Shares": 1830000000.0,
    "Basic Average Shares": 1828000000.0,
    "Diluted EPS": 1.29,
    "Basic EPS": 1.29,
    "Diluted NI Availto Com Stockholders": 2354000000.0,
    "Net Income Common Stockholders": 2354000000.0,
    "Net Income": 2354000000.0,
    "Minority Interests": -1036000000.0,
    "Net Income Including Noncontrolling Interests": 3390000000.0,
    "Net Income Discontinuous Operations": 0.0,
    "Net Income Continuous Operations": 3390000000.0,
    "Tax Provision": 1379000000.0,
    "Pretax Income": 4769000000.0,
    "Other Income Expense": -2674000000.0,
    "Other Non Operating Income Expenses": 368000000.0,
    "Special Income Charges": -3824000000.0,
    "Gain On Sale Of Business": 169000000.0,
    "Other Special Charges": 101000000.0,
    "Restructuring And Mergern Acquisition": 3892000000.0,
    "Earnings From Equity Interest": 782000000.0,
    "Gain On Sale Of Security": 169000000.0,
    "Net Non Operating Interest Income Expense": -1549000000.0,
    "Total Other Finance Cost": -340000000.0,
    "Interest Expense Non Operating": 1973000000.0,
    "Interest Income Non Operating": 424000000.0,
    "Operating Income": 8992000000.0,
    "Operating Expense": 20705000000.0,
    "Depreciation Amortization Depletion Income Statement": 5369000000.0,
    "Depreciation And Amortization In Income Statement": 5369000000.0,
    "Selling General And Administration": 15336000000.0,
    "Gross Profit": 29697000000.0,
    "Cost Of Revenue": 59201000000.0,
    "Total Revenue": 88898000000.0,
    "Operating Revenue": 88898000000.0
  }
}