{
  "symbol": "VZ",
  "year": 2020,
  "report_type": "YearlyIncomeStatement",
  "items": {
    "Tax Effect Of Unusual Items": -818690754.588715,
    "Tax Rate For Calcs": 0.231203,
    "Normalized EBITDA": 52652000000.0,
    "Total Unusual Items": -3541000000.0,
    "Total Unusual Items Excluding Goodwill": -3541000000.0,
    "Net Income From Continuing Operation Net Minority Interest": 22065000000.0,
    "Reconciled Depreciation": 16206000000.0,
    "Reconciled Cost Of Revenue": 56301000000.0,
    "EBITDA": 49111000000.0,
    "EBIT": 32905000000.0,
    "Net Interest Income": -3437000000.0,
    "Interest Expense": 3485000000.0,
    "Interest Income": 48000000.0,
    "Normalized Income": 24787309245.411285,
    "Net Income From Continuing And Discontinued Operation": 22065000000.0,
    "Total Expenses": 101165000000.0,
    "Total Operating Income As Reported": 32448000000.0,
    "Diluted Average Shares": 4150000000.0,
    "Basic Average Shares": 4148000000.0,
    "Diluted EPS": 5.32,
    "Basic EPS": 5.32,
    "Diluted NI Availto Com Stockholders": 22065000000.0,
    "Net Income Common Stockholders": 22065000000.0,
    "Net Income": 22065000000.0,
    "Minority Interests": -553000000.0,
    "Net Income Including Noncontrolling Interests": 22618000000.0,
    "Net Income Continuous Operations": 22618000000.0,
    "Tax Provision": 6802000000.0,
    "Pretax Income": 29420000000.0,
    "Other Income Expense": 409000000.0,
    "Other Non Operating Income Expenses": 3805000000.0,
    "Special Income Charges": -3541000000.0,
    "Other Special Charges": 3541000000.0,
    "Impairment Of Capital Assets": 0.0,
    "Earnings From Equity Interest": 145000000.0,
    "Net Non Operating Interest Income Expense": -3437000000.0,
    "Interest Expense Non Operating": 3485000000.0,
    "Interest Income Non Operating": 48000000.0,
    "Operating Income": 32448000000.0,
    "Operating Expense": 44864000000.0,
    "Depreciation Amortization Depletion Income Statement": 16206000000.0,
    "Depreciation And Amortization In Income Statement": 16206000000.0,
    "Selling General And Administration": 28658000000.0,
    "Gross Profit": 77312000000.0,
    "Cost Of Revenue": 56301000000.0,
    "Total Revenue": 133613000000.0,
    "Operating Revenue": 133613000000.0
  }
}