{
  "symbol": "INTC",
  "period": "2022",
  "report_type": "YearlyIncomeStatement",
  "items": {
    "Tax Effect Of Unusual Items": 21420000.0,
    "Tax Rate For Calcs": 0.21,
    "Normalized EBITDA": 11140000000.0,
    "Total Unusual Items": 102000000.0,
    "Total Unusual Items Excluding Goodwill": 102000000.0,
    "Net Income From Continuing Operation Net Minority Interest": 1689000000.0,
    "Reconciled Depreciation": 9602000000.0,
    "Reconciled Cost Of Revenue": 32517000000.0,
    "EBITDA": 11242000000.0,
    "EBIT": 1640000000.0,
    "Net Interest Income": 629000000.0,
    "Interest Expense": 878000000.0,
    "Interest Income": 1335000000.0,
    "Normalized Income": 1608420000.0,
    "Net Income From Continuing And Discontinued Operation": 1689000000.0,
    "Total Expenses": 54197000000.0,
    "Total Operating Income As Reported": 93000000.0,
    "Diluted Average Shares": 4212000000.0,
    "Basic Average Shares": 4190000000.0,
    "Diluted EPS": 0.4,
    "Basic EPS": 0.4,
    "Diluted NI Availto Com Stockholders": 1689000000.0,
    "Net Income Common Stockholders": 1689000000.0,
    "Net Income": 1689000000.0,
    "Minority Interests": 14000000.0,
    "Net Income Including Noncontrolling Interests": 1675000000.0,
    "Net Income Continuous Operations": 1675000000.0,
    "Tax Provision": -913000000.0,
    "Pretax Income": 762000000.0,
    "Other Income Expense": 102000000.0,
    "Special Income Charges": -152000000.0,
    "Other Special Charges": -329000000.0,
    "Write Off": 259000000.0,
    "Restructuring And Mergern Acquisition": 222000000.0,
    "Gain On Sale Of Security": 254000000.0,
    "Net Non Operating Interest Income Expense": 629000000.0,
    "Total Other Finance Cost": -172000000.0,
    "Interest Expense Non Operating": 878000000.0,
    "Interest Income Non Operating": 1335000000.0,
    "Operating Income": 31000000.0,
    "Operating Expense": 21680000000.0,
    "Research And Development": 16046000000.0,
    "Selling General And Administration": 5634000000.0,
    "Gross Profit": 21711000000.0,
    "Cost Of Revenue": 32517000000.0,
    "Total Revenue": 54228000000.0,
    "Operating Revenue": 54228000000.0
  }
}