{
  "symbol": "MAR",
  "year": 2022,
  "Period": "Q1",
  "report_type": "Q10",
  "metrics": {
    "mdna_sentiment": 0.0,
    "outlook_sentiment": 0.143,
    "forward_ratio": 1.0,
    "hedge_ratio": 0.063
  },
  "top_positive": [
    {
      "sent": "LONG-TERM DEBT We provide detail on our long-term debt balances, net of discounts, premiums, and debt issuance costs, in the following table as of September\u00a030, 2022 and year-end 2021: ($ in millions) September 30, 2022 December 31, 2021 Senior Notes: Series L Notes, interest rate of 3.3 %, face amount of $ 173 , redeemed June 15, 2022 (effective interest rate of 3.4 %) $ \u2014 $ 173 Series P Notes, interest rate of 3.8 %, face amount of $ 350 , maturing October 1, 2025 (effective interest rate of 4.0 %) 348 347 Series Q Notes, interest rate of 2.3 %, face amount of $ 399 , matured January 15, 2022 (effective interest rate of 2.5 %) \u2014 399 Series R Notes, interest rate of 3.1 %, face amount of $ 750 , maturing June 15, 2026 (effective interest rate of 3.3 %) 747 746 Series U Notes, interest rate of 3.1 %, face amount of $ 291 , maturing February\u00a015, 2023 (effective interest rate of 3.1 %) 291 291 Series V Notes, interest rate of 3.8 %, face amount of $ 318 , maturing March\u00a015, 2025 (effective interest rate of 2.8 %) 325 327 Series W Notes, interest rate of 4.5 %, face amount of $ 278 , maturing October\u00a01, 2034 (effective interest rate of 4.1 %) 289 290 Series X Notes, interest rate of 4.0 %, face amount of $ 450 , maturing April\u00a015, 2028 (effective interest rate of 4.2 %) 446 445 Series Z Notes, interest rate of 4.2 %, face amount of $ 350 , maturing December 1, 2023 (effective interest rate of 4.4 %) 349 349 Series AA Notes, interest rate of 4.7 %, face amount of $ 300 , maturing December 1, 2028 (effective interest rate of 4.8 %) 298 297 Series CC Notes, interest rate of 3.6 %, face amount of $ 550 , maturing April 15, 2024 (effective interest rate of 3.9 %) 532 566 Series DD Notes, interest rate of 2.1 %, face amount of $ 224 , matured October 3, 2022 (effective interest rate of 1.2 %) 224 226 Series EE Notes, interest rate of 5.8 %, face amount of $ 600 , maturing May 1, 2025 (effective interest rate of 6.0 %) 596 595 Series FF Notes, interest rate of 4.6 %, face amount of $ 1,000 , maturing June 15, 2030 (effective interest rate of 4.8 %) 988 987 Series GG Notes, interest rate of 3.5 %, face amount of $ 1,000 , maturing October 15, 2032 (effective interest rate of 3.7 %) 986 986 Series HH Notes, interest rate of 2.9 %, face amount of $ 1,100 , maturing April 15, 2031 (effective interest rate of 3.0 %) 1,090 1,090 Series II Notes, interest rate of 2.8 %, face amount of $ 700 , maturing October 15, 2033 (effective interest rate of 2.8 %) 694 693 Series JJ Notes, interest rate of 5.0 %, face amount of $ 1,000 , maturing October 15, 2027 (effective interest rate of 5.4 %) 983 \u2014 Credit Facility \u2014 1,050 Finance lease obligations 141 146 Other 91 135 $ 9,418 $ 10,138 Less current portion ( 558 ) ( 805 ) $ 8,860 $ 9,333 We paid cash for interest, net of amounts capitalized, of $ 203 million in the 2022 first three quarters and $ 251 million in the 2021 first three quarters.",
      "score": 0.9985
    },
    {
      "sent": "LONG-TERM DEBT We provide detail on our long-term debt balances, net of discounts, premiums, and debt issuance costs, in the following table as of September\u00a030, 2022 and year-end 2021: ($ in millions) September 30, 2022 December 31, 2021 Senior Notes: Series L Notes, interest rate of 3.3 %, face amount of $ 173 , redeemed June 15, 2022 (effective interest rate of 3.4 %) $ \u2014 $ 173 Series P Notes, interest rate of 3.8 %, face amount of $ 350 , maturing October 1, 2025 (effective interest rate of 4.0 %) 348 347 Series Q Notes, interest rate of 2.3 %, face amount of $ 399 , matured January 15, 2022 (effective interest rate of 2.5 %) \u2014 399 Series R Notes, interest rate of 3.1 %, face amount of $ 750 , maturing June 15, 2026 (effective interest rate of 3.3 %) 747 746 Series U Notes, interest rate of 3.1 %, face amount of $ 291 , maturing February\u00a015, 2023 (effective interest rate of 3.1 %) 291 291 Series V Notes, interest rate of 3.8 %, face amount of $ 318 , maturing March\u00a015, 2025 (effective interest rate of 2.8 %) 325 327 Series W Notes, interest rate of 4.5 %, face amount of $ 278 , maturing October\u00a01, 2034 (effective interest rate of 4.1 %) 289 290 Series X Notes, interest rate of 4.0 %, face amount of $ 450 , maturing April\u00a015, 2028 (effective interest rate of 4.2 %) 446 445 Series Z Notes, interest rate of 4.2 %, face amount of $ 350 , maturing December 1, 2023 (effective interest rate of 4.4 %) 349 349 Series AA Notes, interest rate of 4.7 %, face amount of $ 300 , maturing December 1, 2028 (effective interest rate of 4.8 %) 298 297 Series CC Notes, interest rate of 3.6 %, face amount of $ 550 , maturing April 15, 2024 (effective interest rate of 3.9 %) 532 566 Series DD Notes, interest rate of 2.1 %, face amount of $ 224 , matured October 3, 2022 (effective interest rate of 1.2 %) 224 226 Series EE Notes, interest rate of 5.8 %, face amount of $ 600 , maturing May 1, 2025 (effective interest rate of 6.0 %) 596 595 Series FF Notes, interest rate of 4.6 %, face amount of $ 1,000 , maturing June 15, 2030 (effective interest rate of 4.8 %) 988 987 Series GG Notes, interest rate of 3.5 %, face amount of $ 1,000 , maturing October 15, 2032 (effective interest rate of 3.7 %) 986 986 Series HH Notes, interest rate of 2.9 %, face amount of $ 1,100 , maturing April 15, 2031 (effective interest rate of 3.0 %) 1,090 1,090 Series II Notes, interest rate of 2.8 %, face amount of $ 700 , maturing October 15, 2033 (effective interest rate of 2.8 %) 694 693 Series JJ Notes, interest rate of 5.0 %, face amount of $ 1,000 , maturing October 15, 2027 (effective interest rate of 5.4 %) 983 \u2014 Credit Facility \u2014 1,050 Finance lease obligations 141 146 Other 91 135 $ 9,418 $ 10,138 Less current portion ( 558 ) ( 805 ) $ 8,860 $ 9,333 We paid cash for interest, net of amounts capitalized, of $ 203 million in the 2022 first three quarters and $ 251 million in the 2021 first three quarters.",
      "score": 0.9985
    },
    {
      "sent": "LONG-TERM DEBT We provide detail on our long-term debt balances, net of discounts, premiums, and debt issuance costs, in the following table as of September\u00a030, 2022 and year-end 2021: ($ in millions) September 30, 2022 December 31, 2021 Senior Notes: Series L Notes, interest rate of 3.3 %, face amount of $ 173 , redeemed June 15, 2022 (effective interest rate of 3.4 %) $ \u2014 $ 173 Series P Notes, interest rate of 3.8 %, face amount of $ 350 , maturing October 1, 2025 (effective interest rate of 4.0 %) 348 347 Series Q Notes, interest rate of 2.3 %, face amount of $ 399 , matured January 15, 2022 (effective interest rate of 2.5 %) \u2014 399 Series R Notes, interest rate of 3.1 %, face amount of $ 750 , maturing June 15, 2026 (effective interest rate of 3.3 %) 747 746 Series U Notes, interest rate of 3.1 %, face amount of $ 291 , maturing February\u00a015, 2023 (effective interest rate of 3.1 %) 291 291 Series V Notes, interest rate of 3.8 %, face amount of $ 318 , maturing March\u00a015, 2025 (effective interest rate of 2.8 %) 325 327 Series W Notes, interest rate of 4.5 %, face amount of $ 278 , maturing October\u00a01, 2034 (effective interest rate of 4.1 %) 289 290 Series X Notes, interest rate of 4.0 %, face amount of $ 450 , maturing April\u00a015, 2028 (effective interest rate of 4.2 %) 446 445 Series Z Notes, interest rate of 4.2 %, face amount of $ 350 , maturing December 1, 2023 (effective interest rate of 4.4 %) 349 349 Series AA Notes, interest rate of 4.7 %, face amount of $ 300 , maturing December 1, 2028 (effective interest rate of 4.8 %) 298 297 Series CC Notes, interest rate of 3.6 %, face amount of $ 550 , maturing April 15, 2024 (effective interest rate of 3.9 %) 532 566 Series DD Notes, interest rate of 2.1 %, face amount of $ 224 , matured October 3, 2022 (effective interest rate of 1.2 %) 224 226 Series EE Notes, interest rate of 5.8 %, face amount of $ 600 , maturing May 1, 2025 (effective interest rate of 6.0 %) 596 595 Series FF Notes, interest rate of 4.6 %, face amount of $ 1,000 , maturing June 15, 2030 (effective interest rate of 4.8 %) 988 987 Series GG Notes, interest rate of 3.5 %, face amount of $ 1,000 , maturing October 15, 2032 (effective interest rate of 3.7 %) 986 986 Series HH Notes, interest rate of 2.9 %, face amount of $ 1,100 , maturing April 15, 2031 (effective interest rate of 3.0 %) 1,090 1,090 Series II Notes, interest rate of 2.8 %, face amount of $ 700 , maturing October 15, 2033 (effective interest rate of 2.8 %) 694 693 Series JJ Notes, interest rate of 5.0 %, face amount of $ 1,000 , maturing October 15, 2027 (effective interest rate of 5.4 %) 983 \u2014 Credit Facility \u2014 1,050 Finance lease obligations 141 146 Other 91 135 $ 9,418 $ 10,138 Less current portion ( 558 ) ( 805 ) $ 8,860 $ 9,333 We paid cash for interest, net of amounts capitalized, of $ 203 million in the 2022 first three quarters and $ 251 million in the 2021 first three quarters.",
      "score": 0.9985
    }
  ],
  "top_negative": [
    {
      "sent": "CONDENSED CONSOLIDATED STATEMENTS OF CASH FLOWS ($ in millions) (Unaudited) Nine Months Ended September 30, 2022 September 30, 2021 OPERATING ACTIVITIES Net income $ 1,685 $ 631 Adjustments to reconcile to cash provided by operating activities: Depreciation, amortization, and other 212 222 Stock-based compensation 144 138 Income taxes 197 ( 292 ) Liability for guest loyalty program ( 17 ) 54 Contract acquisition costs ( 92 ) ( 143 ) Restructuring, merger-related charges, and other ( 1 ) ( 5 ) Working capital changes ( 225 ) 71 Loss on extinguishment of debt \u2014 164 Deferred revenue changes and other 19 ( 95 ) Net cash provided by operating activities 1,922 745 INVESTING ACTIVITIES Capital and technology expenditures ( 192 ) ( 114 ) Dispositions \u2014 8 Loan advances ( 10 ) ( 10 ) Loan collections 12 38 Other 53 ( 3 ) Net cash used in investing activities ( 137 ) ( 81 ) FINANCING ACTIVITIES Credit Facility, net ( 1,050 ) ( 150 ) Issuance of long-term debt 983 1,787 Repayment of long-term debt ( 578 ) ( 2,172 ) Issuance of Class\u00a0A Common Stock \u2014 2 Debt extinguishment costs \u2014 ( 155 ) Dividends paid ( 195 ) \u2014 Purchase of treasury stock ( 1,235 ) \u2014 Stock-based compensation withholding taxes ( 88 ) ( 85 ) Other 25 12 Net cash used in financing activities ( 2,138 ) ( 761 ) DECREASE IN CASH, CASH EQUIVALENTS, AND RESTRICTED CASH ( 353 ) ( 97 ) CASH, CASH EQUIVALENTS, AND RESTRICTED CASH, beginning of period (1) 1,421 894 CASH, CASH EQUIVALENTS, AND RESTRICTED CASH, end of period (1) $ 1,068 $ 797 (1) The 2022 amounts include beginning restricted cash of $ 28 million at December\u00a031, 2021, and ending restricted cash of $ 23 million at September\u00a030, 2022, which we present in the \u201cPrepaid expenses and other\u201d and \u201cOther noncurrent assets\u201d captions of our Balance Sheets.",
      "score": -0.9403
    },
    {
      "sent": "While we believe it is reasonably possible that we may incur losses in excess of the amounts recorded associated with the above described MDL proceedings and regulatory investigations related to the Data Security Incident, it is not possible to reasonably estimate the amount of such losses or range of loss that might result from adverse judgments, settlements, fines, penalties or other resolution of these proceedings and investigations based on: (1) in the case of the above described MDL proceedings, the current stage of these proceedings, the absence of specific allegations as to alleged damages, the uncertainty as to the certification of a class or classes and the size of any certified class, and the lack of resolution of significant factual and legal issues; and (2) in the case of the above described regulatory investigations, the lack of resolution with the Federal Trade Commission and the state Attorneys General.",
      "score": -0.9246
    },
    {
      "sent": "While we believe it is reasonably possible that we may incur losses in excess of the amounts recorded associated with the above described MDL proceedings and regulatory investigations related to the Data Security Incident, it is not possible to reasonably estimate the amount of such losses or range of loss that might result from adverse judgments, settlements, fines, penalties or other resolution of these proceedings and investigations based on: (1) in the case of the above described MDL proceedings, the current stage of these proceedings, the absence of specific allegations as to alleged damages, the uncertainty as to the certification of a class or classes and the size of any certified class, and the lack of resolution of significant factual and legal issues; and (2) in the case of the above described regulatory investigations, the lack of resolution with the Federal Trade Commission and the state Attorneys General.",
      "score": -0.9246
    }
  ],
  "forward_snippets": [
    "Based on the ongoing discussions, we believe it is probable that we will incur losses and have recorded an accrual in the 2022 third quarter for an estimated loss contingency; the amount of this accrual is not material to our Financial Statements.",
    "While we believe it is reasonably possible that we may incur losses in excess of the amounts recorded associated with the above described MDL proceedings and regulatory investigations related to the Data Security Incident, it is not possible to reasonably estimate the amount of such losses or range of loss that might result from adverse judgments, settlements, fines, penalties or other resolution of these proceedings and investigations based on: (1) in the case of the above described MDL proceedings, the current stage of these proceedings, the absence of specific allegations as to alleged damages, the uncertainty as to the certification of a class or classes and the size of any certified class, and the lack of resolution of significant factual and legal issues; and (2) in the case of the above described regulatory investigations, the lack of resolution with the Federal Trade Commission and the state Attorneys General.",
    "We will pay interest on the Series JJ Notes in April and October of each year, commencing in April 2023.",
    "Based on the ongoing discussions, we believe it is probable that we will incur losses and have recorded an accrual in the 2022 third quarter for an estimated loss contingency; the amount of this accrual is not material to our Financial Statements.",
    "While we believe it is reasonably possible that we may incur losses in excess of the amounts recorded associated with the above described MDL proceedings and regulatory investigations related to the Data Security Incident, it is not possible to reasonably estimate the amount of such losses or range of loss that might result from adverse judgments, settlements, fines, penalties or other resolution of these proceedings and investigations based on: (1) in the case of the above described MDL proceedings, the current stage of these proceedings, the absence of specific allegations as to alleged damages, the uncertainty as to the certification of a class or classes and the size of any certified class, and the lack of resolution of significant factual and legal issues; and (2) in the case of the above described regulatory investigations, the lack of resolution with the Federal Trade Commission and the state Attorneys General."
  ],
  "curated_text": "Symbol: MAR. Year: 2022. Period: Q1. ReportType: Q10. Section: Management Discussion and Analysis (MD&A). Key metrics include sentiment, forward outlook, and risk hedging.  Top positive sentences: LONG-TERM DEBT We provide detail on our long-term debt balances, net of discounts, premiums, and debt issuance costs, in the following table as of September\u00a030, 2022 and year-end 2021: ($ in millions) September 30, 2022 December 31, 2021 Senior Notes: Series L Notes, interest rate of 3.3 %, face amount of $ 173 , redeemed June 15, 2022 (effective interest rate of 3.4 %) $ \u2014 $ 173 Series P Notes, interest rate of 3.8 %, face amount of $ 350 , maturing October 1, 2025 (effective interest rate of 4.0 %) 348 347 Series Q Notes, interest rate of 2.3 %, face amount of $ 399 , matured January 15, 2022 (effective interest rate of 2.5 %) \u2014 399 Series R Notes, interest rate of 3.1 %, face amount of $ 750 , maturing June 15, 2026 (effective interest rate of 3.3 %) 747 746 Series U Notes, interest rate of 3.1 %, face amount of $ 291 , maturing February\u00a015, 2023 (effective interest rate of 3.1 %) 291 291 Series V Notes, interest rate of 3.8 %, face amount of $ 318 , maturing March\u00a015, 2025 (effective interest rate of 2.8 %) 325 327 Series W Notes, interest rate of 4.5 %, face amount of $ 278 , maturing October\u00a01, 2034 (effective interest rate of 4.1 %) 289 290 Series X Notes, interest rate of 4.0 %, face amount of $ 450 , maturing April\u00a015, 2028 (effective interest rate of 4.2 %) 446 445 Series Z Notes, interest rate of 4.2 %, face amount of $ 350 , maturing December 1, 2023 (effective interest rate of 4.4 %) 349 349 Series AA Notes, interest rate of 4.7 %, face amount of $ 300 , maturing December 1, 2028 (effective interest rate of 4.8 %) 298 297 Series CC Notes, interest rate of 3.6 %, face amount of $ 550 , maturing April 15, 2024 (effective interest rate of 3.9 %) 532 566 Series DD Notes, interest rate of 2.1 %, face amount of $ 224 , matured October 3, 2022 (effective interest rate of 1.2 %) 224 226 Series EE Notes, interest rate of 5.8 %, face amount of $ 600 , maturing May 1, 2025 (effective interest rate of 6.0 %) 596 595 Series FF Notes, interest rate of 4.6 %, face amount of $ 1,000 , maturing June 15, 2030 (effective interest rate of 4.8 %) 988 987 Series GG Notes, interest rate of 3.5 %, face amount of $ 1,000 , maturing October 15, 2032 (effective interest rate of 3.7 %) 986 986 Series HH Notes, interest rate of 2.9 %, face amount of $ 1,100 , maturing April 15, 2031 (effective interest rate of 3.0 %) 1,090 1,090 Series II Notes, interest rate of 2.8 %, face amount of $ 700 , maturing October 15, 2033 (effective interest rate of 2.8 %) 694 693 Series JJ Notes, interest rate of 5.0 %, face amount of $ 1,000 , maturing October 15, 2027 (effective interest rate of 5.4 %) 983 \u2014 Credit Facility \u2014 1,050 Finance lease obligations 141 146 Other 91 135 $ 9,418 $ 10,138 Less current portion ( 558 ) ( 805 ) $ 8,860 $ 9,333 We paid cash for interest, net of amounts capitalized, of $ 203 million in the 2022 first three quarters and $ 251 million in the 2021 first three quarters. LONG-TERM DEBT We provide detail on our long-term debt balances, net of discounts, premiums, and debt issuance costs, in the following table as of September\u00a030, 2022 and year-end 2021: ($ in millions) September 30, 2022 December 31, 2021 Senior Notes: Series L Notes, interest rate of 3.3 %, face amount of $ 173 , redeemed June 15, 2022 (effective interest rate of 3.4 %) $ \u2014 $ 173 Series P Notes, interest rate of 3.8 %, face amount of $ 350 , maturing October 1, 2025 (effective interest rate of 4.0 %) 348 347 Series Q Notes, interest rate of 2.3 %, face amount of $ 399 , matured January 15, 2022 (effective interest rate of 2.5 %) \u2014 399 Series R Notes, interest rate of 3.1 %, face amount of $ 750 , maturing June 15, 2026 (effective interest rate of 3.3 %) 747 746 Series U Notes, interest rate of 3.1 %, face amount of $ 291 , maturing February\u00a015, 2023 (effective interest rate of 3.1 %) 291 291 Series V Notes, interest rate of 3.8 %, face amount of $ 318 , maturing March\u00a015, 2025 (effective interest rate of 2.8 %) 325 327 Series W Notes, interest rate of 4.5 %, face amount of $ 278 , maturing October\u00a01, 2034 (effective interest rate of 4.1 %) 289 290 Series X Notes, interest rate of 4.0 %, face amount of $ 450 , maturing April\u00a015, 2028 (effective interest rate of 4.2 %) 446 445 Series Z Notes, interest rate of 4.2 %, face amount of $ 350 , maturing December 1, 2023 (effective interest rate of 4.4 %) 349 349 Series AA Notes, interest rate of 4.7 %, face amount of $ 300 , maturing December 1, 2028 (effective interest rate of 4.8 %) 298 297 Series CC Notes, interest rate of 3.6 %, face amount of $ 550 , maturing April 15, 2024 (effective interest rate of 3.9 %) 532 566 Series DD Notes, interest rate of 2.1 %, face amount of $ 224 , matured October 3, 2022 (effective interest rate of 1.2 %) 224 226 Series EE Notes, interest rate of 5.8 %, face amount of $ 600 , maturing May 1, 2025 (effective interest rate of 6.0 %) 596 595 Series FF Notes, interest rate of 4.6 %, face amount of $ 1,000 , maturing June 15, 2030 (effective interest rate of 4.8 %) 988 987 Series GG Notes, interest rate of 3.5 %, face amount of $ 1,000 , maturing October 15, 2032 (effective interest rate of 3.7 %) 986 986 Series HH Notes, interest rate of 2.9 %, face amount of $ 1,100 , maturing April 15, 2031 (effective interest rate of 3.0 %) 1,090 1,090 Series II Notes, interest rate of 2.8 %, face amount of $ 700 , maturing October 15, 2033 (effective interest rate of 2.8 %) 694 693 Series JJ Notes, interest rate of 5.0 %, face amount of $ 1,000 , maturing October 15, 2027 (effective interest rate of 5.4 %) 983 \u2014 Credit Facility \u2014 1,050 Finance lease obligations 141 146 Other 91 135 $ 9,418 $ 10,138 Less current portion ( 558 ) ( 805 ) $ 8,860 $ 9,333 We paid cash for interest, net of amounts capitalized, of $ 203 million in the 2022 first three quarters and $ 251 million in the 2021 first three quarters. LONG-TERM DEBT We provide detail on our long-term debt balances, net of discounts, premiums, and debt issuance costs, in the following table as of September\u00a030, 2022 and year-end 2021: ($ in millions) September 30, 2022 December 31, 2021 Senior Notes: Series L Notes, interest rate of 3.3 %, face amount of $ 173 , redeemed June 15, 2022 (effective interest rate of 3.4 %) $ \u2014 $ 173 Series P Notes, interest rate of 3.8 %, face amount of $ 350 , maturing October 1, 2025 (effective interest rate of 4.0 %) 348 347 Series Q Notes, interest rate of 2.3 %, face amount of $ 399 , matured January 15, 2022 (effective interest rate of 2.5 %) \u2014 399 Series R Notes, interest rate of 3.1 %, face amount of $ 750 , maturing June 15, 2026 (effective interest rate of 3.3 %) 747 746 Series U Notes, interest rate of 3.1 %, face amount of $ 291 , maturing February\u00a015, 2023 (effective interest rate of 3.1 %) 291 291 Series V Notes, interest rate of 3.8 %, face amount of $ 318 , maturing March\u00a015, 2025 (effective interest rate of 2.8 %) 325 327 Series W Notes, interest rate of 4.5 %, face amount of $ 278 , maturing October\u00a01, 2034 (effective interest rate of 4.1 %) 289 290 Series X Notes, interest rate of 4.0 %, face amount of $ 450 , maturing April\u00a015, 2028 (effective interest rate of 4.2 %) 446 445 Series Z Notes, interest rate of 4.2 %, face amount of $ 350 , maturing December 1, 2023 (effective interest rate of 4.4 %) 349 349 Series AA Notes, interest rate of 4.7 %, face amount of $ 300 , maturing December 1, 2028 (effective interest rate of 4.8 %) 298 297 Series CC Notes, interest rate of 3.6 %, face amount of $ 550 , maturing April 15, 2024 (effective interest rate of 3.9 %) 532 566 Series DD Notes, interest rate of 2.1 %, face amount of $ 224 , matured October 3, 2022 (effective interest rate of 1.2 %) 224 226 Series EE Notes, interest rate of 5.8 %, face amount of $ 600 , maturing May 1, 2025 (effective interest rate of 6.0 %) 596 595 Series FF Notes, interest rate of 4.6 %, face amount of $ 1,000 , maturing June 15, 2030 (effective interest rate of 4.8 %) 988 987 Series GG Notes, interest rate of 3.5 %, face amount of $ 1,000 , maturing October 15, 2032 (effective interest rate of 3.7 %) 986 986 Series HH Notes, interest rate of 2.9 %, face amount of $ 1,100 , maturing April 15, 2031 (effective interest rate of 3.0 %) 1,090 1,090 Series II Notes, interest rate of 2.8 %, face amount of $ 700 , maturing October 15, 2033 (effective interest rate of 2.8 %) 694 693 Series JJ Notes, interest rate of 5.0 %, face amount of $ 1,000 , maturing October 15, 2027 (effective interest rate of 5.4 %) 983 \u2014 Credit Facility \u2014 1,050 Finance lease obligations 141 146 Other 91 135 $ 9,418 $ 10,138 Less current portion ( 558 ) ( 805 ) $ 8,860 $ 9,333 We paid cash for interest, net of amounts capitalized, of $ 203 million in the 2022 first three quarters and $ 251 million in the 2021 first three quarters. Top negative sentences: CONDENSED CONSOLIDATED STATEMENTS OF CASH FLOWS ($ in millions) (Unaudited) Nine Months Ended September 30, 2022 September 30, 2021 OPERATING ACTIVITIES Net income $ 1,685 $ 631 Adjustments to reconcile to cash provided by operating activities: Depreciation, amortization, and other 212 222 Stock-based compensation 144 138 Income taxes 197 ( 292 ) Liability for guest loyalty program ( 17 ) 54 Contract acquisition costs ( 92 ) ( 143 ) Restructuring, merger-related charges, and other ( 1 ) ( 5 ) Working capital changes ( 225 ) 71 Loss on extinguishment of debt \u2014 164 Deferred revenue changes and other 19 ( 95 ) Net cash provided by operating activities 1,922 745 INVESTING ACTIVITIES Capital and technology expenditures ( 192 ) ( 114 ) Dispositions \u2014 8 Loan advances ( 10 ) ( 10 ) Loan collections 12 38 Other 53 ( 3 ) Net cash used in investing activities ( 137 ) ( 81 ) FINANCING ACTIVITIES Credit Facility, net ( 1,050 ) ( 150 ) Issuance of long-term debt 983 1,787 Repayment of long-term debt ( 578 ) ( 2,172 ) Issuance of Class\u00a0A Common Stock \u2014 2 Debt extinguishment costs \u2014 ( 155 ) Dividends paid ( 195 ) \u2014 Purchase of treasury stock ( 1,235 ) \u2014 Stock-based compensation withholding taxes ( 88 ) ( 85 ) Other 25 12 Net cash used in financing activities ( 2,138 ) ( 761 ) DECREASE IN CASH, CASH EQUIVALENTS, AND RESTRICTED CASH ( 353 ) ( 97 ) CASH, CASH EQUIVALENTS, AND RESTRICTED CASH, beginning of period (1) 1,421 894 CASH, CASH EQUIVALENTS, AND RESTRICTED CASH, end of period (1) $ 1,068 $ 797 (1) The 2022 amounts include beginning restricted cash of $ 28 million at December\u00a031, 2021, and ending restricted cash of $ 23 million at September\u00a030, 2022, which we present in the \u201cPrepaid expenses and other\u201d and \u201cOther noncurrent assets\u201d captions of our Balance Sheets. While we believe it is reasonably possible that we may incur losses in excess of the amounts recorded associated with the above described MDL proceedings and regulatory investigations related to the Data Security Incident, it is not possible to reasonably estimate the amount of such losses or range of loss that might result from adverse judgments, settlements, fines, penalties or other resolution of these proceedings and investigations based on: (1) in the case of the above described MDL proceedings, the current stage of these proceedings, the absence of specific allegations as to alleged damages, the uncertainty as to the certification of a class or classes and the size of any certified class, and the lack of resolution of significant factual and legal issues; and (2) in the case of the above described regulatory investigations, the lack of resolution with the Federal Trade Commission and the state Attorneys General. While we believe it is reasonably possible that we may incur losses in excess of the amounts recorded associated with the above described MDL proceedings and regulatory investigations related to the Data Security Incident, it is not possible to reasonably estimate the amount of such losses or range of loss that might result from adverse judgments, settlements, fines, penalties or other resolution of these proceedings and investigations based on: (1) in the case of the above described MDL proceedings, the current stage of these proceedings, the absence of specific allegations as to alleged damages, the uncertainty as to the certification of a class or classes and the size of any certified class, and the lack of resolution of significant factual and legal issues; and (2) in the case of the above described regulatory investigations, the lack of resolution with the Federal Trade Commission and the state Attorneys General. Forward-looking snippets: Based on the ongoing discussions, we believe it is probable that we will incur losses and have recorded an accrual in the 2022 third quarter for an estimated loss contingency; the amount of this accrual is not material to our Financial Statements. While we believe it is reasonably possible that we may incur losses in excess of the amounts recorded associated with the above described MDL proceedings and regulatory investigations related to the Data Security Incident, it is not possible to reasonably estimate the amount of such losses or range of loss that might result from adverse judgments, settlements, fines, penalties or other resolution of these proceedings and investigations based on: (1) in the case of the above described MDL proceedings, the current stage of these proceedings, the absence of specific allegations as to alleged damages, the uncertainty as to the certification of a class or classes and the size of any certified class, and the lack of resolution of significant factual and legal issues; and (2) in the case of the above described regulatory investigations, the lack of resolution with the Federal Trade Commission and the state Attorneys General. We will pay interest on the Series JJ Notes in April and October of each year, commencing in April 2023. Based on the ongoing discussions, we believe it is probable that we will incur losses and have recorded an accrual in the 2022 third quarter for an estimated loss contingency; the amount of this accrual is not material to our Financial Statements. While we believe it is reasonably possible that we may incur losses in excess of the amounts recorded associated with the above described MDL proceedings and regulatory investigations related to the Data Security Incident, it is not possible to reasonably estimate the amount of such losses or range of loss that might result from adverse judgments, settlements, fines, penalties or other resolution of these proceedings and investigations based on: (1) in the case of the above described MDL proceedings, the current stage of these proceedings, the absence of specific allegations as to alleged damages, the uncertainty as to the certification of a class or classes and the size of any certified class, and the lack of resolution of significant factual and legal issues; and (2) in the case of the above described regulatory investigations, the lack of resolution with the Federal Trade Commission and the state Attorneys General."
}