{
  "symbol": "WBD",
  "year": 2023,
  "metrics": {
    "mdna_sentiment": 0.3749,
    "outlook_sentiment": 0.25,
    "forward_ratio": 1.0,
    "hedge_ratio": 0.186
  },
  "top_positive": [
    {
      "sent": "TrendGroupLLCMember 2022-12-31 0001437107 disca:MotorTrendGroupLLCMember 2021-12-31 0001437107 disca:OtherNoncontrollingInterestsMember 2022-12-31 0001437107 disca:OtherNoncontrollingInterestsMember 2021-12-31 0001437107 disca:HasbroIncMember disca:DiscoveryFamilyMember 2021-12-31 0001437107 disca:MotorTrendGroupLLCJointVentureMember 2017-09-01 2017-09-30 0001437107 disca:GoldenTreeAssetManagementLPMember disca:MotorTrendGroupLLCJointVentureMember 2017-12-31 0001437107 disca:MotorTrendGroupLLCJointVentureMember 2022-12-31 0001437107 disca:TheFoodNetworkandCookingChannelMember disca:TribuneMediaCompanyMember 2022-12-31 0001437107 srt:BoardOfDirectorsChairmanMember disca:LibertyGlobalMember 2022-12-31 0001437107 srt:BoardOfDirectorsChairmanMember disca:LibertyBroadbandMember 2022-12-31 0001437107 disca:LibertyGroupMember 2022-01-01 2022-12-31 0001437107 disca:LibertyGroupMember 2021-01-01 2021-12-31 0001437107 disca:LibertyGroupMember 2020-01-01 2020-12-31 0001437107 us-gaap:EquityMethodInvestmentsMember 2022-01-01 2022-12-31 0001437107 us-gaap:EquityMethodInvestmentsMember 2021-01-01 2021-12-31 0001437107 us-gaap:EquityMethodInvestmentsMember 2020-01-01 2020-12-31 0001437107 disca:OtherrelatedpartiesMember 2022-01-01 2022-12-31 0001437107 disca:OtherrelatedpartiesMember 2021-01-01 2021-12-31 0001437107 disca:OtherrelatedpartiesMember 2020-01-01 2020-12-31 0001437107 disca:ContentMember 2022-12-31 0001437107 us-gaap:OtherCreditDerivativesMember 2022-12-31 0001437107 disca:OtherEmployeeObligationsMember 2022-12-31 0001437107 us-gaap:OtherCreditDerivativesMember srt:MinimumMember 2022-01-01 2022-12-31 0001437107 us-gaap:OtherCreditDerivativesMember srt:MaximumMember 2022-01-01 2022-12-31 0001437107 disca:SixFlagsGuaranteeMember 2022-12-31 0001437107 disca:SixFlagsGuaranteeMember 2022-01-01 2022-12-31 0001437107 disca:StudiosSegmentMember 2020-01-01 2020-12-31 0001437107 disca:NetworksSegmentMember 2020-01-01 2020-12-31 0001437107 disca:DTCSegmentMember 2020-01-01 2020-12-31 0001437107 country:US 2022-01-01 2022-12-31 0001437107 country:US 2021-01-01 2021-12-31 0001437107 country:US 2020-01-01 2020-12-31 0001437107 us-gaap:NonUsMember 2022-01-01 2022-12-31 0001437107 us-gaap:NonUsMember 2021-01-01 2021-12-31 0001437107 us-gaap:NonUsMember 2020-01-01 2020-12-31 0001437107 country:US 2022-12-31 0001437107 country:US 2021-12-31 0001437107 country:GB 2022-12-31 0001437107 country:GB 2021-12-31 0001437107 disca:NonUSorUKMember 2022-12-31 0001437107 disca:NonUSorUKMember 2021-12-31 0001437107 us-gaap:AllowanceForCreditLossMember 2021-12-31 0001437107 us-gaap:AllowanceForCreditLossMember 2022-01-01 2022-12-31 0001437107 us-gaap:AllowanceForCreditLossMember 2022-12-31 0001437107 us-gaap:ValuationAllowanceOfDeferredTaxAssetsMember 2021-12-31 0001437107 us-gaap:ValuationAllowanceOfDeferredTaxAssetsMember 2022-01-01 2022-12-31 0001437107 us-gaap:ValuationAllowanceOfDeferredTaxAssetsMember 2022-12-31 0001437107 us-gaap:AllowanceForCreditLossMember 2020-12-31 0001437107 us-gaap:AllowanceForCreditLossMember 2021-01-01 2021-12-31 0001437107 us-gaap:ValuationAllowanceOfDeferredTaxAssetsMember 2020-12-31 0001437107 us-gaap:ValuationAllowanceOfDeferredTaxAssetsMember 2021-01-01 2021-12-31 0001437107 us-gaap:AllowanceForCreditLossMember 2019-12-31 0001437107 us-gaap:AllowanceForCreditLossMember 2020-01-01 2020-12-31 0001437107 us-gaap:AccountingStandardsUpdate201613Member us-gaap:AllowanceForCreditLossMember srt:CumulativeEffectPeriodOfAdoptionAdjustmentMember 2020-01-01 2020-12-31 0001437107 us-gaap:ValuationAllowanceOfDeferredTaxAssetsMember 2019-12-31 0001437107 us-gaap:ValuationAllowanceOfDeferredTaxAssetsMember 2020-01-01 2020-12-31 UNITED STATES SECURITIES AND EXCHANGE COMMISSION Washington, D.C.",
      "score": 0.7555
    },
    {
      "sent": "20549 FORM 10-K \u2612 ANNUAL REPORT PURSUANT TO SECTION 13 OR 15(d) OF THE SECURITIES EXCHANGE ACT OF 1934 For the fiscal year ended December 31 , 2022 OR \u2610 TRANSITION REPORT PURSUANT TO SECTION 13 OR 15(d) OF THE SECURITIES EXCHANGE ACT OF 1934 For the transition period from\u00a0\u00a0\u00a0\u00a0\u00a0\u00a0\u00a0\u00a0\u00a0\u00a0\u00a0\u00a0\u00a0\u00a0\u00a0\u00a0\u00a0\u00a0\u00a0\u00a0 to Commission File Number: 001-34177 Warner Bros.",
      "score": 0.7324
    },
    {
      "sent": "Employer Identification No.) 230 Park Avenue South 10003 New York , New York (Zip Code) (Address of principal executive offices) ( 212 ) 548-5555 (Registrant\u2019s telephone number, including area code) Securities registered pursuant to Section\u00a012(b) of the Act: Title of Each Class Trading Symbols Name of Each Exchange on Which Registered Series A Common Stock WBD The Nasdaq Global Select Market Securities registered pursuant to Section\u00a012(g) of the Act: None Indicate by check mark if the Registrant is a well-known seasoned issuer, as defined in Rule\u00a0405 of the Securities Act.",
      "score": 0.7096
    },
    {
      "sent": "Year Ended December 31, 2022 Pension Plan SERP Accumulated benefit obligation $ 746 $ 16 Change in projected benefit obligation: Projected benefit obligation at beginning of year $ 82 $ 22 Amounts assumed upon acquisition (See Note 4) 907 1 Service cost 2 \u2014 Interest cost 21 \u2014 Benefits paid ( 35 ) ( 1 ) Actuarial gains ( 225 ) ( 6 ) Settlement charges ( 6 ) \u2014 Projected benefit obligation at end of year 746 16 Plan assets: Fair value at beginning of year 63 \u2014 Amounts assumed upon acquisition (See Note 4) 756 \u2014 Actual return on plan assets ( 268 ) \u2014 Company contributions 23 1 Benefits paid ( 35 ) ( 1 ) Settlement charges ( 6 ) \u2014 Fair value at end of year 533 \u2014 Under funded status $ ( 213 ) $ ( 16 ) Amounts recognized as assets and liabilities on the consolidated balance sheets: Other noncurrent assets $ 92 $ \u2014 Accrued liabilities ( 27 ) ( 2 ) Other noncurrent liabilities ( 278 ) ( 14 ) Total $ ( 213 ) $ ( 16 ) Amounts recognized in accumulated other comprehensive (gain) loss consist of: Net loss (gain) $ 97 $ ( 3 ) The weighted average assumptions used to determine benefit obligations were as follows.",
      "score": 0.979
    },
    {
      "sent": "December 31, 2022 Total Level 1 Level 2 Level 3 Equity securities $ 69 $ 34 $ 35 $ \u2014 Fixed income securities 532 14 446 72 Multi-asset credit fund 21 \u2014 21 \u2014 Cash 5 5 \u2014 \u2014 Total plan assets measured at fair value $ 627 $ 53 $ 502 $ 72 Assets held at net asset value practical expedient Real assets $ 22 Hedge funds 20 Total assets held at net asset value practical expedient $ 42 Liabilities: Derivatives ( 136 ) \u2014 ( 136 ) \u2014 Total plan assets $ 533 The table below sets forth a summary of changes in the fair value of the Level 3 pension assets for the year ended December 31, 2022 (in millions).",
      "score": 0.979
    }
  ],
  "top_negative": [
    {
      "sent": "Such disruptions may be caused by power outages, natural disasters, extreme weather, terrorist attacks, war, failures or impairments of communications satellites or on-ground uplinks or downlinks or other technical facilities and services used to transmit programming, failure of service providers to meet contractual requirements, or other similar events.",
      "score": -0.9694
    },
    {
      "sent": "The following is a list of some, but not all, of the factors that could cause actual results or events to differ materially from those anticipated: \u2022 potential unknown liabilities, adverse consequences or unforeseen increased expenses associated with the WarnerMedia Business or our efforts to integrate the WarnerMedia Business; \u2022 inherent uncertainties involved in the estimates and assumptions used in the preparation of financial forecasts; \u2022 our level of debt, including the significant indebtedness incurred in connection with the acquisition of the WarnerMedia Business, and our future compliance with debt covenants; \u2022 more intense competitive pressure from existing or new competitors in the industries in which we operate; \u2022 reduced spending on domestic and foreign television advertising, due to macroeconomic trends, industry trends or unexpected reductions in our number of subscribers; \u2022 industry trends, including the timing of, and spending on, sports programming, feature film, television and television commercial production; \u2022 market demand for foreign first-run and existing content libraries; \u2022 negative publicity or damage to our brands, reputation or talent; \u2022 uncertainties associated with product and service development and market acceptance, including the development and provision of programming for new television and telecommunications technologies, and the success of our HBO Max and discovery+ streaming products; \u2022 realizing direct-to-consumer subscriber goals; \u2022 general economic and business conditions, including the impact of the ongoing COVID-19 pandemic, fluctuations in foreign currency exchange rates, and political unrest in the international markets in which we operate; \u2022 the possibility or duration of an industry-wide strike, player lock-outs or other job action affecting a major entertainment industry union, athletes or others involved in the development and production of our sports programming, television programming, feature films and interactive entertainment (e.g., games) who are covered by collective bargaining agreements; \u2022 disagreements with our distributors or other business partners; \u2022 continued consolidation of distribution customers and production studios; \u2022 theft of our content and unauthorized duplication, distribution and exhibition of such content; \u2022 threatened or actual cyber-attacks and cybersecurity breaches; and \u2022 changes in, or failure or inability to comply with, laws and government regulations, including, without limitation, regulations of the Federal Communications Commission and similar authorities internationally and data privacy regulations and adverse outcomes from regulatory proceedings.",
      "score": -0.9604
    },
    {
      "sent": "The following is a list of some, but not all, of the factors that could cause actual results or events to differ materially from those anticipated: \u2022 potential unknown liabilities, adverse consequences or unforeseen increased expenses associated with the WarnerMedia Business or our efforts to integrate the WarnerMedia Business; \u2022 inherent uncertainties involved in the estimates and assumptions used in the preparation of financial forecasts; \u2022 our level of debt, including the significant indebtedness incurred in connection with the acquisition of the WarnerMedia Business, and our future compliance with debt covenants; \u2022 more intense competitive pressure from existing or new competitors in the industries in which we operate; \u2022 reduced spending on domestic and foreign television advertising, due to macroeconomic trends, industry trends or unexpected reductions in our number of subscribers; \u2022 industry trends, including the timing of, and spending on, sports programming, feature film, television and television commercial production; \u2022 market demand for foreign first-run and existing content libraries; \u2022 negative publicity or damage to our brands, reputation or talent; \u2022 uncertainties associated with product and service development and market acceptance, including the development and provision of programming for new television and telecommunications technologies, and the success of our HBO Max and discovery+ streaming products; \u2022 realizing direct-to-consumer subscriber goals; \u2022 general economic and business conditions, including the impact of the ongoing COVID-19 pandemic, fluctuations in foreign currency exchange rates, and political unrest in the international markets in which we operate; \u2022 the possibility or duration of an industry-wide strike, player lock-outs or other job action affecting a major entertainment industry union, athletes or others involved in the development and production of our sports programming, television programming, feature films and interactive entertainment (e.g., games) who are covered by collective bargaining agreements; \u2022 disagreements with our distributors or other business partners; \u2022 continued consolidation of distribution customers and production studios; \u2022 theft of our content and unauthorized duplication, distribution and exhibition of such content; \u2022 threatened or actual cyber-attacks and cybersecurity breaches; and \u2022 changes in, or failure or inability to comply with, laws and government regulations, including, without limitation, regulations of the Federal Communications Commission and similar authorities internationally and data privacy regulations and adverse outcomes from regulatory proceedings.",
      "score": -0.9604
    }
  ],
  "forward_snippets": [
    "Impact of COVID-19 We continue to closely monitor the ongoing impact of COVID-19 on all aspects of our business and geographies; however, the nature and full extent of COVID-19\u2019s effects on our operations and results are not yet known and will depend on future developments, which are highly uncertain and cannot be predicted.",
    "We expect to rebrand and relaunch the HBO Max product in the U.S.",
    "We expect to have both an ad-lite and an ad-free version of the expanded product in many markets.",
    "We expect to rebrand and relaunch the HBO Max product in the U.S.",
    "We expect to have both an ad-lite and an ad-free version of the expanded product in many markets."
  ]
}